random_user_agent/__init__.py
random_user_agent/params.py
random_user_agent/user_agent.py
random_user_agent/data/user_agents.zip
random_user_agent-1.0.0.dist-info/METADATA
random_user_agent-1.0.0.dist-info/RECORD
random_user_agent-1.0.0.dist-info/WHEEL
random_user_agent-1.0.0.dist-info/top_level.txt
