Metadata-Version: 2.1
Name: random-user-agent
Version: 1.0.0
Summary: A package to get random user agents based filters provided by user
Home-page: https://github.com/Luqman-Ud-Din/random_user_agent
Author: Luqman-Ud-Din Muhammad
Author-email: luqmanuddinm@gmail.com
License: MIT
Platform: UNKNOWN
Classifier: Programming Language :: Python :: 3
Classifier: License :: OSI Approved :: MIT License
Classifier: Operating System :: OS Independent
